Metadata-Version: 2.1
Name: earthworth
Version: 0.1
Summary: Good one maths
Author: Divyanshi
License: UNKNOWN
Platform: UNKNOWN
